CHANGES.txt
README.txt
bootstrap.py
buildout.cfg
setup.py
src/p01/__init__.py
src/p01.releaser.egg-info/PKG-INFO
src/p01.releaser.egg-info/SOURCES.txt
src/p01.releaser.egg-info/dependency_links.txt
src/p01.releaser.egg-info/namespace_packages.txt
src/p01.releaser.egg-info/not-zip-safe
src/p01.releaser.egg-info/requires.txt
src/p01.releaser.egg-info/top_level.txt
src/p01/releaser/README.txt
src/p01/releaser/__init__.py
src/p01/releaser/base.py
src/p01/releaser/changes.txt
src/p01/releaser/package.py
src/p01/releaser/pypi.py
src/p01/releaser/tests.py